MANIFEST.in
README.rst
setup.cfg
setup.py
sprox/__init__.py
sprox/_compat.py
sprox/_validatorselector.py
sprox/_widgetselector.py
sprox/configbase.py
sprox/dummyentity.py
sprox/entitiesbase.py
sprox/fillerbase.py
sprox/formbase.py
sprox/iprovider.py
sprox/metadata.py
sprox/providerselector.py
sprox/recordviewbase.py
sprox/release.py
sprox/saormprovider.py
sprox/sprockets.py
sprox/tablebase.py
sprox/util.py
sprox/validators.py
sprox/validatorselector.py
sprox/viewbase.py
sprox/widgetselector.py
sprox.egg-info/PKG-INFO
sprox.egg-info/SOURCES.txt
sprox.egg-info/dependency_links.txt
sprox.egg-info/entry_points.txt
sprox.egg-info/not-zip-safe
sprox.egg-info/requires.txt
sprox.egg-info/top_level.txt
sprox/mg/__init__.py
sprox/mg/provider.py
sprox/mg/validatorselector.py
sprox/mg/widgetselector.py
sprox/sa/__init__.py
sprox/sa/provider.py
sprox/sa/support.py
sprox/sa/validatorselector.py
sprox/sa/widgetselector.py
sprox/widgets/__init__.py
sprox/widgets/tw1widgets/__init__.py
sprox/widgets/tw1widgets/widgets.py
sprox/widgets/tw1widgets/templates/__init__.py
sprox/widgets/tw1widgets/templates/checkbox.html
sprox/widgets/tw1widgets/templates/checkbox.mak
sprox/widgets/tw1widgets/templates/container.html
sprox/widgets/tw1widgets/templates/datagrid.html
sprox/widgets/tw1widgets/templates/datagrid.mak
sprox/widgets/tw1widgets/templates/entityDef.html
sprox/widgets/tw1widgets/templates/entityLabel.html
sprox/widgets/tw1widgets/templates/hidden_put.html
sprox/widgets/tw1widgets/templates/hidden_put.mak
sprox/widgets/tw1widgets/templates/modelLabel.html
sprox/widgets/tw1widgets/templates/recordField.html
sprox/widgets/tw1widgets/templates/recordViewTable.html
sprox/widgets/tw1widgets/templates/table.html
sprox/widgets/tw1widgets/templates/tableDef.html
sprox/widgets/tw1widgets/templates/tableForm.html
sprox/widgets/tw1widgets/templates/tableLabel.html
sprox/widgets/tw1widgets/test/__init__.py
sprox/widgets/tw2widgets/__init__.py
sprox/widgets/tw2widgets/widgets.py
sprox/widgets/tw2widgets/templates/__init__.py
sprox/widgets/tw2widgets/templates/container.html
sprox/widgets/tw2widgets/templates/datagrid.genshi
sprox/widgets/tw2widgets/templates/datagrid.kajiki
