Metadata-Version: 2.1
Name: sprox
Version: 0.11.2
Summary: A package for creation of web widgets directly from database schema.
Home-page: http://www.sprox.org
Author: Christopher Perkins, Michael Brickenstein, Alessandro Molina
Author-email: chris@percious.com, amol@turbogears.org
License: MIT
Platform: UNKNOWN
Classifier: Development Status :: 4 - Beta
Classifier: Intended Audience :: Developers
Classifier: License :: OSI Approved :: MIT License
Classifier: Programming Language :: Python
Classifier: Topic :: Internet :: WWW/HTTP
Classifier: Topic :: Internet :: WWW/HTTP :: Dynamic Content
Classifier: Topic :: Software Development :: Libraries :: Python Modules
Provides-Extra: testing
